guomin/__init__.py
guomin/my_module.py
llt/__init__.py
llt/my_module.py
guomin-0.1.dist-info/METADATA
guomin-0.1.dist-info/WHEEL
guomin-0.1.dist-info/top_level.txt
guomin-0.1.dist-info/RECORD
