Metadata-Version: 2.1
Name: guomin
Version: 0.1
Summary: guomin 的第一个包
Author: liulitao
